kazm/__init__.py
kazm/ai/__init__.py
kazm/ai/ai_engine.py
kazm/ai/base.py
kazm/ai/groq_provider.py
kazm/config.py
kazm/game/sus.py
kazm/settings.ini.REMOVE
kazm/utils.py
kazm-0.0.22.dist-info/LICENSE
kazm-0.0.22.dist-info/METADATA
kazm-0.0.22.dist-info/WHEEL
kazm-0.0.22.dist-info/RECORD
