Metadata-Version: 2.3
Name: kazm
Version: 0.0.22
Summary: A fully modular AI game backend built in python
License: GPL-3.0
Author: hamad
Author-email: 60110135+HAlafeefi@users.noreply.github.com
Requires-Python: >=3.10
Classifier: License :: OSI Approved :: GNU General Public License v3 (GPLv3)
Classifier: Programming Language :: Python :: 3
Classifier: Programming Language :: Python :: 3.10
Classifier: Programming Language :: Python :: 3.11
Classifier: Programming Language :: Python :: 3.12
Classifier: Programming Language :: Python :: 3.13
Provides-Extra: all
Provides-Extra: groq
Requires-Dist: groq ; extra == "all"
Requires-Dist: groq ; extra == "groq"
Requires-Dist: python-dotenv (>=1.1.0,<2.0.0)
Project-URL: Changelog, https://github.com/HAlafeefi/kazm/releases
Project-URL: Documentation, https://github.com/HAlafeefi/kazm
Project-URL: Homepage, https://github.com/HAlafeefi/kazm
Project-URL: Issues, https://github.com/HAlafeefi/kazm/issues
Project-URL: Repository, https://github.com/HAlafeefi/kazm
